Lab9/DataMemory.v
`timescale 1ns / 1ps

`define SIZE 1024

module DataMemory(ReadData , Address , WriteData , MemoryRead , MemoryWrite , Clock);
   input [63:0]      WriteData;
   input [63:0]      Address;
   input             Clock, MemoryRead, MemoryWrite;
   output reg [63:0] ReadData;

   reg [7:0] 	     memBank [`SIZE-1:0];


   // This task is used to write arbitrary data to the Data Memory by
   // the intialization block.
   task initset;
      input [63:0] addr;
      input [63:0] data;
      begin
	 memBank[addr] =  data[63:56] ; // Big-endian for the win...
	 memBank[addr+1] =  data[55:48];
	 memBank[addr+2] =  data[47:40];
	 memBank[addr+3] =  data[39:32];
	 memBank[addr+4] =  data[31:24];
	 memBank[addr+5] =  data[23:16];
	 memBank[addr+6] =  data[15:8];
	 memBank[addr+7] =  data[7:0];
      end
   endtask


   initial
     begin
        // preseting some data in the data memory used by test #1

        // Address 0x0 gets 0x1
        initset( 64'h0,  64'h1);  //Counter variable
        initset( 64'h8,  64'ha);  //Part of mask
        initset( 64'h10, 64'h5);  //Other part of mask
        initset( 64'h18, 64'h0ffbea7deadbeeff); //big constant
        initset( 64'h20, 64'h0); //clearing space

        // Add any data you need for your tests here.

     end

   // This always block reads the data memory and places a double word
   // on the ReadData bus.
   always @(posedge Clock)
     begin
        if(MemoryRead)
          begin
             ReadData[63:56] <=  memBank[Address];
             ReadData[55:48] <=  memBank[Address+1];
             ReadData[47:40] <=  memBank[Address+2];
             ReadData[39:32] <=  memBank[Address+3];
             ReadData[31:24] <=  memBank[Address+4];
             ReadData[23:16] <=  memBank[Address+5];
             ReadData[15:8] <=  memBank[Address+6];
             ReadData[7:0] <=  memBank[Address+7];
          end
          //$display("LDUR %h",ReadData);
     end

   // This always block takes data from the WriteData bus and writes
   // it into the DataMemory.
   always @(posedge Clock)
     begin
        if(MemoryWrite)
          begin
             memBank[Address] <= #3 WriteData[63:56] ;
             memBank[Address+1] <= #3 WriteData[55:48];
             memBank[Address+2] <= #3 WriteData[47:40];
             memBank[Address+3] <= #3 WriteData[39:32];
             memBank[Address+4] <= #3 WriteData[31:24];
             memBank[Address+5] <= #3 WriteData[23:16];
             memBank[Address+6] <= #3 WriteData[15:8];
             memBank[Address+7] <= #3 WriteData[7:0];
             // Could be useful for debugging:
             // $display("Writing Address:%h Data:%h",Address, WriteData);
          end
     end
endmodule

Lab9/SignExtender.v
module SignExtender(BusImm, Imm26, Ctrl, shift); 
   output reg [63:0] BusImm; 
   input [25:0]  Imm26; 
   input [2:0] Ctrl; 
   input [1:0] shift;
   
   //assign extBit = (Ctrl ? 2'b0 : Imm16[25]); //1'b0->2'b00 , 15->25
   //assign BusImm = {{26{extBit}}, Imm16}; //25->26 
   
   //-----------------
  always@(*) 
	begin
		case(Ctrl)
			3'b000: BusImm = {52'b0, Imm26[21:10]}; //ALUImm
			3'b001: BusImm = {{55{Imm26[20]}}, Imm26[20:12]}; //DTaddr
			3'b010: BusImm = {{36{Imm26[25]}}, Imm26, 2'b0}; //Baddr
			3'b011: BusImm = {{43{Imm26[23]}}, Imm26[23:5], 2'b0}; //CondBaddr
			
			3'b100: case(shift)
			   2'b00: BusImm = {48'b0, Imm26[20:5]}; //move immediate
			   2'b01: BusImm = {32'b0, Imm26[20:5], 16'b0};
			   2'b10: BusImm = {16'b0, Imm26[20:5], 32'b0};
			   2'b11: BusImm = {Imm26[20:5], 48'b0};
			   endcase
		endcase
	end
endmodule
   //assign ALUImm = {52'b0, ALU_immediate}
   //assign DTaddr = {55{DT_address[8]}, DT_address}
   //assign Baddr = {36{BR_address[25]}, BR_address, 2'b0}
   //assign CondBaddr = {43{COND_BR_address[25]}, COND_BR_address, 2'b0}

Lab9/RegisterFile.v
`timescale 1ns / 1ps
module RegisterFile(BusA, BusB, BusW, RW, RA, RB, RegWr, Clk);
    output [63:0] BusA;
    output [63:0] BusB;
    input [63:0] BusW;
    input [4:0] RW, RA, RB;
    input RegWr;
    input Clk;
    reg [63:0] registers [31:0];
     
    assign #2 BusA = (RA!=5'd31)?registers[RA]:64'h0;
    assign #2 BusB = (RB!=5'd31)?registers[RB]:64'h0;
    
    
     
    always @ (negedge Clk) begin
        //$display("[!]BusA = %h",BusA);
        //$display("[!]BusB = %h",BusB);
      // $display("*REG[1] = %h",registers[1]);
      // $display("*REG[2] = %h",registers[2]);
      // $display("*REG[3] = %h",registers[3]);
      // $display("*REG[4] = %h",registers[4]);
      //  $display("*REG[9] = %h",registers[9]);
        if((RW != 31) && RegWr) //stores BusW into RW register
            registers[RW] <= #3 BusW;
          //  $display("*jREG[9] = %h",registers[9]);
          //  $display("*REG[10] = %h",registers[10]);
          //  $display("*REG[11] = %h",registers[11]);
          //$display("*REG[12] = %h",registers[12]);
          //  $display("*REG[13] = %h",registers[13]);
          //  $display("*RW = %d",RW);
          //  $display("*BusW = %h",BusW);
        
    end
endmodule

Lab9/NextPClogic.v
module NextPClogic(NextPC, CurrentPC, SignExtImm64, Branch, ALUZero, Uncondbranch); 
   input [63:0] CurrentPC, SignExtImm64; 
   input 	Branch, ALUZero, Uncondbranch; 
   output reg [63:0] NextPC; 

   /* write your code here */ 
   always@* begin
   
   /*
   if(!Uncondbranch & !Branch) begin
   //$display("Testing not U. not B %h Next is %h", CurrentPC, NextPC);
      assign NextPC = CurrentPC + 64'b1;
     // $display("After not U. not B %h Next is %h", CurrentPC, NextPC);
   end
   else if(Uncondbranch & !Branch) begin
     // $display("Testing U. not B");
      assign NextPC = SignExtImm64;
   end
   else if(!Uncondbranch & Branch) begin
      //$display("Testing not U, B");
      if(ALUZero) begin
         assign NextPC = SignExtImm64;
      end 
      else if(!ALUZero) begin
         assign NextPC = CurrentPC + 1'b1;
      end
   end
   */
  // assign [63:0] shiftSign = SignExtImm64 << 2;
   if((Branch && ALUZero) || Uncondbranch) begin
      NextPC = SignExtImm64 + CurrentPC;
      $display("NextPC %h, Branch&zero %b signout %h",NextPC,Branch && ALUZero,SignExtImm64);
   end 
   else begin
      NextPC = CurrentPC + 4'h4;
   end
   
   end
   
   /*
   if branch & zero or uncondbranch
      add signext shifted 4 with the pc
   otherwise
      just add 4
   
   
   
   
   */
   

   initial       
      if(Branch==1'b1&&ALUZero==1'b1)
         $display("NexPC %h",NextPC);
endmodule

Lab9/ALU.v
`define AND   4'b0000
`define OR    4'b0001
`define ADD   4'b0010
`define SUB   4'b0110
`define PassB 4'b0111


module ALU(BusW, BusA, BusB, ALUCtrl, Zero);
    
    output  reg [63:0] BusW;
    input   [63:0] BusA, BusB;
    input   [3:0] ALUCtrl;
    output  Zero;
    
    //reg     [63:0] BusW;
    assign Zero = (BusW==64'b0)?1'b1:1'b0;
    always @(*) begin
       // $display("BUSA %b",BusA);
       // $display("BUSB %b",BusB);
       //$display("BUSW %b",BusW);
       //$display("ALU Zero %b",Zero);
       // $display("ALU CTRL %h",ALUCtrl);
        case(ALUCtrl)
            `AND: begin
                BusW = BusA & BusB;
            end
            `OR: begin
                BusW = BusA | BusB;
            end
            `ADD: begin
                BusW = BusA + BusB;
            end
            `SUB: begin
                BusW = BusA - BusB;
            end
            `PassB: begin
                //if(BusA < BusB) begin BusW = 1; Zero = 0; end
                //else begin BusW = 0; Zero = 1; end
                BusW = BusB;
            end
            
        endcase
    end

        
endmodule

Lab9/SingleCycleControl.v
`define OPCODE_ANDREG 11'b?0001010???
`define OPCODE_ORRREG 11'b?0101010???
`define OPCODE_ADDREG 11'b?0?01011???
`define OPCODE_SUBREG 11'b?1?01011???

`define OPCODE_ADDIMM 11'b?0?10001???
`define OPCODE_SUBIMM 11'b?1?10001???

`define OPCODE_MOVZ   11'b110100101??

`define OPCODE_B      11'b?00101?????
`define OPCODE_CBZ    11'b?011010????

`define OPCODE_LDUR   11'b??111000010
`define OPCODE_STUR   11'b??111000000

`timescale 1ns / 1ps

module SingleCycleControl(
	       output reg 	reg2loc,
	       output reg 	alusrc,
	       output reg 	mem2reg,
	       output reg 	regwrite,
	       output reg 	memread,
	       output reg 	memwrite,
	       output reg 	branch,
	       output reg 	uncond_branch,
	       output reg [3:0] aluop,
	       output reg [2:0] signop,
	       output reg [1:0] shift,
	       input [10:0] 	opcode
	       );

   always @(*)
     begin
	casez (opcode)

          /* Add cases here for each instruction your processor supports */
	  
	  `OPCODE_LDUR: begin
	  	    //$display("Goes through LDUR ALOT ^^^^^^^^^^^^^^^^^^^^^^^^^^^^^^^^^^^^^^^^^^^^^^^^^^^^^^^^^^^^^^^^^^^^^^^^^^^^^^^^^^^^^^^^^^^^^");
	       reg2loc       = 1'b1; //was an x
	       uncond_branch = 1'b0;
	       branch        = 1'b0;
	       memread       = 1'b1;
	       mem2reg       = 1'b1;
	       memwrite      = 1'b0;
               alusrc        = 1'b1;
               regwrite      = 1'b1;
               aluop         = 4'b0010;
               signop        = 3'b001;
	       shift         = 2'b00;
            end
	    `OPCODE_STUR: begin
	       reg2loc       = 1'b1;
	       uncond_branch = 1'b0;
	       branch        = 1'b0;
	       memread       = 1'b0;
	       mem2reg       = 1'b0; //was an x
	       memwrite      = 1'b1;
               alusrc        = 1'b1;
               regwrite      = 1'b0;
               aluop         = 4'b0010;
               signop        = 3'b001;
	       shift         = 2'b00;
            end
	    `OPCODE_ADDIMM: begin
	       reg2loc       = 1'b1; //was an x
	       uncond_branch = 1'b0;
	       branch        = 1'b0;
	       memread       = 1'b0;
	       mem2reg       = 1'b0;
	       memwrite      = 1'b0;
               alusrc        = 1'b1; //or 0
               regwrite      = 1'b1;
               aluop         = 4'b0010;
               signop        = 3'b000;
	       shift         = 2'b00;
            end
	    `OPCODE_ADDREG: begin
	       reg2loc       = 1'b0;
	       uncond_branch = 1'b0;
	       branch        = 1'b0;
	       memread       = 1'b0;
	       mem2reg       = 1'b0;
	       memwrite      = 1'b0;
               alusrc        = 1'b0; //or 1
               regwrite      = 1'b1;
               aluop         = 4'b0010;
               signop        = 3'b001;
	       shift         = 2'b00;
            end
	    `OPCODE_SUBIMM: begin
	       reg2loc       = 1'b0;
	       uncond_branch = 1'b0;
	       branch        = 1'b0;
	       memread       = 1'b0;
	       mem2reg       = 1'b0;
	       memwrite      = 1'b0;
               alusrc        = 1'b0; //or 0
               regwrite      = 1'b1;
               aluop         = 4'b0110;
               signop        = 3'b000;
	       shift         = 2'b00;
            end
	    `OPCODE_SUBREG: begin
	       reg2loc       = 1'b0;
	       uncond_branch = 1'b0;
	       branch        = 1'b0;
	       memread       = 1'b0;
	       mem2reg       = 1'b0;
	       memwrite      = 1'b0;
               alusrc        = 1'b0; //or 1
               regwrite      = 1'b1;
               aluop         = 4'b0110;
               signop        = 3'b001;
	       shift         = 2'b00;
            end
	    `OPCODE_ANDREG: begin
	       reg2loc       = 1'b0;
	       uncond_branch = 1'b0;
	       branch        = 1'b0;
	       memread       = 1'b0;
	       mem2reg       = 1'b0;
	       memwrite      = 1'b0;
               alusrc        = 1'b0;
               regwrite      = 1'b1;
               aluop         = 4'b0000;
               signop        = 3'b001;
	       shift         = 2'b00;
            end
	    `OPCODE_ORRREG: begin
	       reg2loc       = 1'b0;
	       uncond_branch = 1'b0;
	       branch        = 1'b0;
	       memread       = 1'b0;
	       mem2reg       = 1'b0;
	       memwrite      = 1'b0;
               alusrc        = 1'b0;
               regwrite      = 1'b1;
               aluop         = 4'b0001;
               signop        = 3'b001;
	       shift         = 2'b00;
            end
	    `OPCODE_CBZ: begin
	       reg2loc       = 1'b1;
	       uncond_branch = 1'b0;
	       branch        = 1'b1;
	       memread       = 1'b0;
	       mem2reg       = 1'b1;
	       memwrite      = 1'b0;
               alusrc        = 1'b0;
               regwrite      = 1'b0;
               aluop         = 4'b0111;
               signop        = 3'b011;
	       shift         = 2'b00;
            end
	    `OPCODE_B: begin
	       reg2loc       = 1'b0;
	       uncond_branch = 1'b1;
	       branch        = 1'b0;
	       memread       = 1'b0;
	       mem2reg       = 1'b0;
	       memwrite      = 1'b0;
               alusrc        = 1'b0;
               regwrite      = 1'b0;
               aluop         = 4'b0000;
               signop        = 3'b010;
	       shift         = 2'b00;
            end
	    
	    `OPCODE_MOVZ: begin
	       reg2loc       = 1'b0;
	       uncond_branch = 1'b0;
	       branch        = 1'b0;
	       memread       = 1'b0;
	       mem2reg       = 1'b0;
	       memwrite      = 1'b0;
               alusrc        = 1'b1;
               regwrite      = 1'b1;
               aluop         = 4'b0111;
               signop        = 3'b100;
	       shift         = opcode[1:0];
            end
	  

          default:
            begin
	    //$display("Goes through this ALOT");
               reg2loc       = 1'b0; //was an x
               alusrc        = 1'b0; //was an x
               mem2reg       = 1'b0; //was an x
               regwrite      = 1'b0;
               memread       = 1'b0;
               memwrite      = 1'b0;
               branch        = 1'b0;
               uncond_branch = 1'b0;
               aluop         = 4'b0000; //was an x
               signop        = 3'b000; //was an x
	       shift         = 2'b00;
            end
	endcase
     end

endmodule

Lab9/InstructionMemory.v
`timescale 1ns / 1ps
/*
 * Module: InstructionMemory
 *
 * Implements read-only instruction memory
 * 
 */
module InstructionMemory(Data, Address);
   parameter T_rd = 20;
   parameter MemSize = 40;
   
   output [31:0] Data;
   input [63:0]  Address;
   reg [31:0] 	 Data;
   
   /*
    * ECEN 350 Processor Test Functions
    * Texas A&M University
    */
   
   always @ (Address) begin

      case(Address)

	/* Test Program 1:
	 * Program loads constants from the data memory. Uses these constants to test
	 * the following instructions: LDUR, ORR, AND, CBZ, ADD, SUB, STUR and B.
	 * 
	 * Assembly code for test:
	 * 
	 * 0: LDUR X9, [XZR, 0x0]    //Load 1 into x9
	 * 4: LDUR X10, [XZR, 0x8]   //Load a into x10
	 * 8: LDUR X11, [XZR, 0x10]  //Load 5 into x11
	 * C: LDUR X12, [XZR, 0x18]  //Load big constant into x12
	 * 10: LDUR X13, [XZR, 0x20]  //load a 0 into X13
	 * 
	 * 14: ORR X10, X10, X11  //Create mask of 0xf
	 * 18: AND X12, X12, X10  //Mask off low order bits of big constant
	 * 
	 * loop:
	 * 1C: CBZ X12, end  //while X12 is not 0
	 * 20: ADD X13, X13, X9  //Increment counter in X13
	 * 24: SUB X12, X12, X9  //Decrement remainder of big constant in X12
	 * 28: B loop  //Repeat till X12 is 0
	 * 2C: STUR X13, [XZR, 0x20]  //store back the counter value into the memory location 0x20
	 */
	//$display("^^^^^^^^^^^");
	63'h000: Data = 32'hF84003E9;
	//$display("&&&&&&&&&&&&&&&&&&&&&&&&&&&&&&&&&&&&&&&&&&&&&&&&&&&&&&&&&&&&&&&&&&&&&&&&&&&&&&&&&&&&&&&&&&&&");
	63'h004: Data = 32'hF84083EA;
	//$display("&&&&&&&&&&&&&&&&&&&&&&&&&&&&&&&&&&&&&&&&&&&&&&&&&&&&&&&&&&&&&&&&&&&&&&&&&&&&&&&&&&&&&&");
	63'h008: Data = 32'hF84103EB;
	//$display("&&&&&&&&&&&&&&&&&&&&&&&&&&&&&&&&&&&&&&&&&&&&&&&&&&&&&&&&&&&&&&&&&&&&&&&&&&&&&&&");
	63'h00c: Data = 32'hF84183EC;
	//$display("&&&&&&&&&&&&&&&&&&&&&&&&&&&&&&&&&&&&&&&&&&&&&&&&&&&&&&&&&&&&&&&&&&&&&&&&&");
	63'h010: Data = 32'hF84203ED;
	63'h014: Data = 32'hAA0B014A;
	63'h018: Data = 32'h8A0A018C;
	63'h01c: Data = 32'hB400008C;
	63'h020: Data = 32'h8B0901AD;
	63'h024: Data = 32'hCB09018C;
	63'h028: Data = 32'h17FFFFFD;
	63'h02c: Data = 32'hF80203ED;
	//$display("passed 2c");
	63'h030: Data = 32'hF84203ED;  //One last load to place stored value on memdbus for test checking.

	/* Add code for your tests here */
	
	63'h034: Data = 32'hD2E24681;
	63'h038: Data = 32'hD2cACF02;
	63'h03c: Data = 32'hD2B35783;
	63'h040: Data = 32'hD29BDE04;
	63'h044: Data = 32'h8B020029;
	63'h048: Data = 32'h8B030129;
	63'h04c: Data = 32'h8B040129;
	63'h050: Data = 32'hF80283E9;
	63'h054: Data = 32'hF84283EA;

	
	default: Data = 32'hXXXXXXXX;
      endcase
   end
endmodule

Lab9/SingleCycleProc.v
/*
module ALU(BusW, BusA, BusB, ALUCtrl, Zero);
module NextPClogic(NextPC, CurrentPC, SignExtImm64, Branch, ALUZero, Uncondbranch);
module SignExtender(BusImm, Imm26, Ctrl); 
module RegisterFile(BusA, BusB, BusW, RW, RA, RB, RegWr, Clk);
module InstructionMemory(Data, Address);
*/

`timescale 1ns / 1ps
module singlecycle(
		   input 	     resetl,
		   input [63:0]      startpc,
		   output reg [63:0] currentpc,
		   output [63:0]     MemtoRegOut,  // this should be
						   // attached to the
						   // output of the
						   // MemtoReg Mux
		   input 	     CLK
		   );

   // Next PC connections
   wire [63:0] 			     nextpc;       // The next PC, to be updated on clock cycle

   // Instruction Memory connections
   wire [31:0] 			     instruction;  // The current instruction

   // Parts of instruction
   wire [4:0] 			     rd;            // The destination register
   wire [4:0] 			     rm;            // Operand 1
   wire [4:0] 			     rn;            // Operand 2
   wire [10:0] 			     opcode;

   // Control wires
   wire 			     reg2loc;
   wire 			     alusrc;
   wire 			     mem2reg;
   wire 			     regwrite;
   wire 			     memread;
   wire 			     memwrite;
   wire 			     branch;
   wire 			     uncond_branch;
   wire [3:0] 			     aluctrl;
   wire [2:0] 			     signop;
   wire [1:0]			     shift;

   // Register file connections
   wire [63:0] 			     regoutA;     // Output A
   wire [63:0] 			     regoutB;     // Output B
  // wire [63:0] BusW;

   // ALU connections
   wire [63:0] 			     aluout;
   wire 			     zero;

   // Sign Extender connections
   wire [63:0] 			     extimm;

   // PC update logic
   always @(negedge CLK)
     begin
        if (resetl) begin
          currentpc <= #3 nextpc;
	  //$display("LDUR %h",MemtoRegOut);
	  //$display("Branch %b ALUZero %b",branch,zero);
        end else 
          currentpc <= #3 startpc;
     end
   // Parts of instruction
   assign rd = instruction[4:0];
   assign rm = instruction[9:5];
   assign rn = reg2loc ? instruction[4:0] : instruction[20:16];
   assign opcode = instruction[31:21];
   wire [63:0] alumux;
   assign alumux = alusrc ? extimm : regoutB;
   wire [63:0] MemOut;
   assign MemtoRegOut = mem2reg ? MemOut : aluout;

   InstructionMemory imem(
			  .Data(instruction),
			  .Address(currentpc)
			  );

   SingleCycleControl control(
		   .reg2loc(reg2loc),
		   .alusrc(alusrc),
		   .mem2reg(mem2reg),
		   .regwrite(regwrite),
		   .memread(memread),
		   .memwrite(memwrite),
		   .branch(branch),
		   .uncond_branch(uncond_branch),
		   .aluop(aluctrl),
		   .signop(signop),
		   .shift(shift),
		   .opcode(opcode)
		   );

   /*
    * Connect the remaining datapath elements below.
    * Do not forget any additional multiplexers that may be required.
    */
    
    ALU alu(.BusW(aluout), .BusA(regoutA), .BusB(alumux), .ALUCtrl(aluctrl), .Zero(zero));
    NextPClogic npc(.NextPC(nextpc), .CurrentPC(currentpc), .SignExtImm64(extimm), .Branch(branch), .ALUZero(zero), .Uncondbranch(uncond_branch));
    RegisterFile regfile(.BusA(regoutA), .BusB(regoutB), .BusW(MemtoRegOut), .RW(rd), .RA(rm), .RB(rn), .RegWr(regwrite), .Clk(CLK));
    SignExtender signext(.BusImm(extimm), .Imm26(instruction[25:0]), .Ctrl(signop), .shift(shift)); 
    DataMemory datam(.ReadData(MemOut) , .Address(aluout) , .WriteData(regoutB) , .MemoryRead(memread) , .MemoryWrite(memwrite) , .Clock(CLK));
    



endmodule

Lab9/SingleCycleProcTest.v
`timescale 1ns / 1ps

`define STRLEN 32
`define HalfClockPeriod 60
`define ClockPeriod `HalfClockPeriod * 2

module SingleCycleProcTest_v;

   initial
     begin
        $dumpfile("singlecycle.vcd");
        $dumpvars;
     end

   // These tasks are used to check if a given test has passed and
   // confirm that all tests passed.
   task passTest;
      input [63:0] actualOut, expectedOut;
      input [`STRLEN*8:0] testType;
      inout [7:0] 	  passed;

      if(actualOut == expectedOut) begin $display ("%s passed", testType); passed = passed + 1; end
      else $display ("%s failed: 0x%x should be 0x%x", testType, actualOut, expectedOut);
   endtask

   task allPassed;
      input [7:0] passed;
      input [7:0] numTests;

      if(passed == numTests) $display ("All tests passed");
      else $display("Some tests failed: %d of %d passed", passed, numTests);
   endtask

   // Inputs
   reg 		  CLK;
   reg 		  Reset_L;
   reg [63:0] 	  startPC;
   reg [7:0] 	  passed;
   reg [15:0] 	  watchdog;

   // Outputs
   wire [63:0] 	  MemtoRegOut;
   wire [63:0] 	  currentPC;

   // Instantiate the Unit Under Test (UUT)
   singlecycle uut (
		    .CLK(CLK),
		    .resetl(Reset_L),
		    .startpc(startPC),
		    .currentpc(currentPC),
		    .MemtoRegOut(MemtoRegOut)
		    );

   initial begin
      // Initialize Inputs
      Reset_L = 1;
      startPC = 0;
      passed = 0;

      // Initialize Watchdog timer
      watchdog = 0;

      // Wait for global reset
      #(1 * `ClockPeriod);

      // Program 1
      #1
        Reset_L = 0; startPC = 0;
      @(posedge CLK);
      @(negedge CLK);
      @(posedge CLK);
      Reset_L = 1;

      // ***********************************************************
      // This while loop will continue cycling the processor until the
      // PC reaches the final instruction in the first test.  If the
      // program forms an infinite loop, never reaching the end, the
      // watchdog timer will kick in and kill simulation after 64K
      // cycles.
      // ***********************************************************

      while (currentPC < 64'h30)
        begin
	   @(posedge CLK);
	   @(negedge CLK);
           $display("CurrentPC:%h",currentPC);
        end
      passTest(MemtoRegOut, 64'hF, "Results of Program 1", passed);

      // ***********************************************************
      // Add your new tests here
      // ***********************************************************
      while (currentPC < 64'h54)
        begin
	   @(posedge CLK);
	   @(negedge CLK);
           $display("CurrentPC:%h",currentPC);
        end
      passTest(MemtoRegOut, 64'h123456789ABCDEF0, "Results of Program 2", passed);
      // Done
      allPassed(passed, 2);   // Be sure to change the one to match
      // the number of tests you add.
      $finish;
   end

   // Initialize the clock to be 0
   initial begin
      CLK = 0;
   end

   // The following is correct if clock starts at LOW level at StartTime //
   always begin
      #`HalfClockPeriod CLK = ~CLK;
      #`HalfClockPeriod CLK = ~CLK;
      watchdog = watchdog +1;
   end

   // Kill the simulation if the watchdog hits 64K cycles
   always @*
     if (watchdog == 16'hFF)
       begin
          $display("Watchdog Timer Expired.");
          $finish;
       end


endmodule

Lab9/singlecycle.vcd
$date
	Wed Nov 16 21:36:47 2022
$end
$version
	Icarus Verilog
$end
$timescale
	1ps
$end
$scope module SingleCycleProcTest_v $end
$var wire 64 ! currentPC [63:0] $end
$var wire 64 " MemtoRegOut [63:0] $end
$var reg 1 # CLK $end
$var reg 1 $ Reset_L $end
$var reg 8 % passed [7:0] $end
$var reg 64 & startPC [63:0] $end
$var reg 16 ' watchdog [15:0] $end
$scope module uut $end
$var wire 1 # CLK $end
$var wire 1 $ resetl $end
$var wire 64 ( startpc [63:0] $end
$var wire 1 ) zero $end
$var wire 1 * uncond_branch $end
$var wire 3 + signop [2:0] $end
$var wire 2 , shift [1:0] $end
$var wire 5 - rn [4:0] $end
$var wire 5 . rm [4:0] $end
$var wire 1 / regwrite $end
$var wire 64 0 regoutB [63:0] $end
$var wire 64 1 regoutA [63:0] $end
$var wire 1 2 reg2loc $end
$var wire 5 3 rd [4:0] $end
$var wire 11 4 opcode [10:0] $end
$var wire 64 5 nextpc [63:0] $end
$var wire 1 6 memwrite $end
$var wire 1 7 memread $end
$var wire 1 8 mem2reg $end
$var wire 32 9 instruction [31:0] $end
$var wire 64 : extimm [63:0] $end
$var wire 1 ; branch $end
$var wire 1 < alusrc $end
$var wire 64 = aluout [63:0] $end
$var wire 64 > alumux [63:0] $end
$var wire 4 ? aluctrl [3:0] $end
$var wire 64 @ MemtoRegOut [63:0] $end
$var wire 64 A MemOut [63:0] $end
$var reg 64 B currentpc [63:0] $end
$scope module alu $end
$var wire 64 C BusB [63:0] $end
$var wire 1 ) Zero $end
$var wire 64 D BusA [63:0] $end
$var wire 4 E ALUCtrl [3:0] $end
$var reg 64 F BusW [63:0] $end
$upscope $end
$scope module control $end
$var wire 11 G opcode [10:0] $end
$var reg 4 H aluop [3:0] $end
$var reg 1 < alusrc $end
$var reg 1 ; branch $end
$var reg 1 8 mem2reg $end
$var reg 1 7 memread $end
$var reg 1 6 memwrite $end
$var reg 1 2 reg2loc $end
$var reg 1 / regwrite $end
$var reg 2 I shift [1:0] $end
$var reg 3 J signop [2:0] $end
$var reg 1 * uncond_branch $end
$upscope $end
$scope module datam $end
$var wire 64 K Address [63:0] $end
$var wire 1 # Clock $end
$var wire 1 7 MemoryRead $end
$var wire 1 6 MemoryWrite $end
$var wire 64 L WriteData [63:0] $end
$var reg 64 M ReadData [63:0] $end
$scope task initset $end
$var reg 64 N addr [63:0] $end
$var reg 64 O data [63:0] $end
$upscope $end
$upscope $end
$scope module imem $end
$var wire 64 P Address [63:0] $end
$var reg 32 Q Data [31:0] $end
$upscope $end
$scope module npc $end
$var wire 1 ) ALUZero $end
$var wire 1 ; Branch $end
$var wire 64 R CurrentPC [63:0] $end
$var wire 1 * Uncondbranch $end
$var wire 64 S SignExtImm64 [63:0] $end
$var reg 64 T NextPC [63:0] $end
$upscope $end
$scope module regfile $end
$var wire 64 U BusW [63:0] $end
$var wire 1 # Clk $end
$var wire 5 V RA [4:0] $end
$var wire 5 W RB [4:0] $end
$var wire 5 X RW [4:0] $end
$var wire 1 / RegWr $end
$var wire 64 Y BusB [63:0] $end
$var wire 64 Z BusA [63:0] $end
$upscope $end
$scope module signext $end
$var wire 3 [ Ctrl [2:0] $end
$var wire 26 \ Imm26 [25:0] $end
$var wire 2 ] shift [1:0] $end
$var reg 64 ^ BusImm [63:0] $end
$upscope $end
$upscope $end
$scope task allPassed $end
$var reg 8 _ numTests [7:0] $end
$var reg 8 ` passed [7:0] $end
$upscope $end
$scope task passTest $end
$var reg 64 a actualOut [63:0] $end
$var reg 64 b expectedOut [63:0] $end
$var reg 8 c passed [7:0] $end
$var reg 257 d testType [256:0] $end
$upscope $end
$upscope $end
$enddefinitions $end
#0
$dumpvars
bx d
bx c
bx b
bx a
bx `
bx _
bx ^
bx ]
bx \
bx [
bx Z
bx Y
bx X
bx W
bx V
bx U
bx T
bx S
bx R
bx Q
bx P
b0 O
b100000 N
bx M
bx L
bx K
bx J
bx I
bx H
bx G
bx F
bx E
bx D
bx C
bx B
bx A
bx @
bx ?
bx >
bx =
x<
x;
bx :
bx 9
x8
x7
x6
bx 5
bx 4
bx 3
x2
bx 1
bx 0
x/
bx .
bx -
bx ,
bx +
x*
x)
b0 (
b0 '
b0 &
b0 %
1$
0#
bx "
bx !
$end
#60000
1#
#120000
b1 '
0#
#121000
0$
#180000
1#
#240000
b10 '
0#
#243000
b0 >
b0 C
b0 :
b0 S
b0 ^
b0 ,
b0 I
b0 ]
b1 +
b1 J
b1 [
b10 ?
b10 E
b10 H
1/
1<
06
18
17
0;
0*
12
b1001 -
b1001 W
b10000000000001111101001 \
b11111000010 4
b11111000010 G
b11111 .
b11111 V
b1001 3
b1001 X
b11111000010000000000001111101001 9
b11111000010000000000001111101001 Q
b100 5
b100 T
b0 !
b0 B
b0 P
b0 R
#245000
1)
b0 =
b0 F
b0 K
b0 1
b0 D
b0 Z
#300000
b1 "
b1 @
b1 U
b1 A
b1 M
1$
1#
#360000
b11 '
0#
#363000
0)
b1000 =
b1000 F
b1000 K
b1000 >
b1000 C
b1000 :
b1000 S
b1000 ^
b1010 -
b1010 W
b10000001000001111101010 \
b1010 3
b1010 X
b11111000010000001000001111101010 9
b11111000010000001000001111101010 Q
b1000 5
b1000 T
b100 !
b100 B
b100 P
b100 R
#420000
b1010 "
b1010 @
b1010 U
b1010 A
b1010 M
1#
#480000
b100 '
0#
#483000
b10000 =
b10000 F
b10000 K
b10000 >
b10000 C
b10000 :
b10000 S
b10000 ^
b1011 -
b1011 W
b10000010000001111101011 \
b1011 3
b1011 X
b11111000010000010000001111101011 9
b11111000010000010000001111101011 Q
b1100 5
b1100 T
b1000 !
b1000 B
b1000 P
b1000 R
#540000
b101 "
b101 @
b101 U
b101 A
b101 M
1#
#600000
b101 '
0#
#603000
b11000 =
b11000 F
b11000 K
b11000 >
b11000 C
b11000 :
b11000 S
b11000 ^
b1100 -
b1100 W
b10000011000001111101100 \
b1100 3
b1100 X
b11111000010000011000001111101100 9
b11111000010000011000001111101100 Q
b10000 5
b10000 T
b1100 !
b1100 B
b1100 P
b1100 R
#660000
b111111111011111010100111110111101010110110111110111011111111 "
b111111111011111010100111110111101010110110111110111011111111 @
b111111111011111010100111110111101010110110111110111011111111 U
b111111111011111010100111110111101010110110111110111011111111 A
b111111111011111010100111110111101010110110111110111011111111 M
1#
#720000
b110 '
0#
#723000
b100000 =
b100000 F
b100000 K
b100000 >
b100000 C
b100000 :
b100000 S
b100000 ^
b1101 -
b1101 W
b10000100000001111101101 \
b1101 3
b1101 X
b11111000010000100000001111101101 9
b11111000010000100000001111101101 Q
b10100 5
b10100 T
b10000 !
b10000 B
b10000 P
b10000 R
#780000
b0 "
b0 @
b0 U
b0 A
b0 M
1#
#840000
b111 '
0#
#843000
x)
bx =
bx F
bx K
bx >
bx C
bx "
bx @
bx U
b10110000 :
b10110000 S
b10110000 ^
b1 ?
b1 E
b1 H
0<
08
07
02
b1011 -
b1011 W
b10000010110000000101001010 \
b10101010000 4
b10101010000 G
b1010 .
b1010 V
b1010 3
b1010 X
b10101010000010110000000101001010 9
b10101010000010110000000101001010 Q
b11000 5
b11000 T
b10100 !
b10100 B
b10100 P
b10100 R
#845000
0)
b1111 "
b1111 @
b1111 U
b1111 =
b1111 F
b1111 K
b101 >
b101 C
b1010 1
b1010 D
b1010 Z
b101 0
b101 L
b101 Y
#900000
1#
#960000
b1000 '
0#
