Lab8/NextPClogic.v
module NextPClogic(NextPC, CurrentPC, SignExtImm64, Branch, ALUZero, Uncondbranch); 
   input [63:0] CurrentPC, SignExtImm64; 
   input 	Branch, ALUZero, Uncondbranch; 
   output reg [63:0] NextPC; 

   /* write your code here */ 
   always@* begin
   
   /*
   if(!Uncondbranch & !Branch) begin
   //$display("Testing not U. not B %h Next is %h", CurrentPC, NextPC);
      assign NextPC = CurrentPC + 64'b1;
     // $display("After not U. not B %h Next is %h", CurrentPC, NextPC);
   end
   else if(Uncondbranch & !Branch) begin
     // $display("Testing U. not B");
      assign NextPC = SignExtImm64;
   end
   else if(!Uncondbranch & Branch) begin
      //$display("Testing not U, B");
      if(ALUZero) begin
         assign NextPC = SignExtImm64;
      end 
      else if(!ALUZero) begin
         assign NextPC = CurrentPC + 1'b1;
      end
   end
   */
  // assign [63:0] shiftSign = SignExtImm64 << 2;
   if((Branch && ALUZero) || Uncondbranch) begin
      assign NextPC = (SignExtImm64 << 2) + CurrentPC;
   end
   else begin
      assign NextPC = CurrentPC + 4'h4;
   end
   
   end
   
   /*
   if branch & zero or uncondbranch
      add signext shifted 4 with the pc
   otherwise
      just add 4
   
   
   
   
   */
   


endmodule

Lab8/NextPCLogicTest.v
`timescale 1ns / 1ps

`define STRLEN 15
module NextPCLogicTest;

   initial
     begin
      $dumpfile("NextPCLogicTest.vcd");
      $dumpvars(0,NextPCLogicTest);
     end
     	
	task passTest;
		input [64:0] actualOut, expectedOut;
		input [`STRLEN*8:0] testType;
		inout [7:0] passed;
	
		if(actualOut == expectedOut) begin $display ("%s passed", testType); passed = passed + 1; end
		else $display ("%s failed: %x should be %x", testType, actualOut, expectedOut);
	endtask
	
	task allPassed;
		input [7:0] passed;
		input [7:0] numTests;
		
		if(passed == numTests) $display ("All tests passed");
		else $display("Some tests failed");
	endtask

	// Inputs
	
	reg [63:0] CurrentPC;
	reg [63:0] SignExtImm64;
	reg Branch;
	reg ALUZero;
	reg Uncondbranch;
	reg [7:0] passed;

	// Outputs
	wire [63:0] NextPC;

	// Instantiate the Unit Under Test (UUT)
	NextPClogic uut (
		.CurrentPC(CurrentPC), 
		.SignExtImm64(SignExtImm64), 
		.Branch(Branch), 
		.Uncondbranch(Uncondbranch), 
		.ALUZero(ALUZero),
		.NextPC(NextPC)
	);

	initial begin
		// Initialize Inputs
	CurrentPC=0;
	SignExtImm64=0;
	Branch=0;
	ALUZero=0;
	Uncondbranch=0;
	passed=0;

                // Here is one example test vector, testing the ADD instruction:
         
		{CurrentPC, SignExtImm64, Branch, ALUZero, Uncondbranch} = {64'h1, 64'hABCD0000, 1'b0, 1'b0, 1'b0}; #40; passTest(NextPC, 64'h5, " test Uncond =F and B = F", passed); //normal and no zero pos
		{CurrentPC, SignExtImm64, Branch, ALUZero, Uncondbranch} = {64'h1, 64'hABCD0000, 1'b0, 1'b1, 1'b0}; #40; passTest(NextPC, 64'h5, " test Uncond =F and B = F", passed); //normal and zero pos
		{CurrentPC, SignExtImm64, Branch, ALUZero, Uncondbranch} = {64'h1, -64'hABCD0000, 1'b0, 1'b0, 1'b0}; #40; passTest(NextPC, 64'h5, " test Uncond =F and B = F", passed); //normal and no zero neg
		{CurrentPC, SignExtImm64, Branch, ALUZero, Uncondbranch} = {64'h1, -64'hABCD0000, 1'b0, 1'b1, 1'b0}; #40; passTest(NextPC, 64'h5, " test Uncond =F and B = F", passed); //normal and zero neg
		
		{CurrentPC, SignExtImm64, Branch, ALUZero, Uncondbranch} = {64'h1, 64'hABCD0000, 1'b1, 1'b0, 1'b0}; #40; passTest(NextPC, 64'h5, " test Uncond =F and B = F", passed); //cond and no zero pos
		{CurrentPC, SignExtImm64, Branch, ALUZero, Uncondbranch} = {64'h1, 64'h1, 1'b1, 1'b1, 1'b0}; #40; passTest(NextPC, 64'h5, " test Uncond =F and B = F", passed); //cond and zero pos
		{CurrentPC, SignExtImm64, Branch, ALUZero, Uncondbranch} = {64'h1, {{62'b1},{2'b00}}, 1'b1, 1'b0, 1'b0}; #40; passTest(NextPC, 64'h5, " test #2 Uncond =T and B = F", passed); //cond and no zero neg
		{CurrentPC, SignExtImm64, Branch, ALUZero, Uncondbranch} = {64'h9, -64'h1, 1'b1, 1'b1, 1'b0}; #40; passTest(NextPC, 64'h5, " test #2 Uncond =T and B = F", passed); //cond and zero neg

		
		{CurrentPC, SignExtImm64, Branch, ALUZero, Uncondbranch} = {64'h1, 64'h1, 1'b0, 1'b0, 1'b1}; #40; passTest(NextPC, 64'h5, " test Uncond =F and B = F", passed); //unncond and no zero pos
		{CurrentPC, SignExtImm64, Branch, ALUZero, Uncondbranch} = {64'h1, 64'h1, 1'b0, 1'b0, 1'b1}; #40; passTest(NextPC, 64'h5, " test Uncond =F and B = F", passed); //uncond and zero pos
		{CurrentPC, SignExtImm64, Branch, ALUZero, Uncondbranch} = {64'h9, -64'h1, 1'b0, 1'b0, 1'b1}; #40; passTest(NextPC, 64'h5, " test Uncond =F and B = F", passed); //uncond and no zero neg
		{CurrentPC, SignExtImm64, Branch, ALUZero, Uncondbranch} = {64'h9, -64'h1, 1'b0, 1'b0, 1'b1}; #40; passTest(NextPC, 64'h5, " test Uncond =F and B = F", passed); //uncond and zero neg
		
		/*
		{CurrentPC, SignExtImm64, Branch, ALUZero, Uncondbranch} = {64'h1, 64'h1111, 1'b0, 1'b1, 1'b0}; #40; passTest(NextPC, 64'h5, " test #1 Uncond =T and B = F", passed);
		{CurrentPC, SignExtImm64, Branch, ALUZero, Uncondbranch} = {64'h1, 64'h0004, 1'b0, 1'b1, 1'b1}; #40; passTest(NextPC, 64'h0005, " test #2 Uncond =T and B = F", passed);
		
		{CurrentPC, SignExtImm64, Branch, ALUZero, Uncondbranch} = {64'h1, , 1'b1, 1'b0, 1'b0}; #40; passTest(NextPC, 64'h0005, " test #2 Uncond =T and B = F", passed);
		{CurrentPC, SignExtImm64, Branch, ALUZero, Uncondbranch} = {64'h9, {{62'b1},{2'b00}}, 1'b1, 1'b1, 1'b0}; #40; passTest(NextPC, 64'h0005, " test #2 Uncond =T and B = F", passed);
		
		{CurrentPC, SignExtImm64, Branch, ALUZero, Uncondbranch} = {64'h1, 64'h1111, 1'b1, 1'b1, 1'b0}; #40; passTest(NextPC, 64'h1111, " test ALU = T", passed);
		{CurrentPC, SignExtImm64, Branch, ALUZero, Uncondbranch} = {64'h1, 64'h1111, 1'b1, 1'b0, 1'b0}; #40; passTest(NextPC, 64'h2, " test ALU = F", passed);
		
		{CurrentPC, SignExtImm64, Branch, ALUZero, Uncondbranch} = {64'h3, 64'h1111, 1'b1, 1'b0, 1'b0}; #40; passTest(NextPC, 64'h4, " test ALU = F", passed);
		{CurrentPC, SignExtImm64, Branch, ALUZero, Uncondbranch} = {64'h3, 64'h1111, 1'b1, 1'b1, 1'b0}; #40; passTest(NextPC, 64'h1111, " test ALU = T", passed);
		*/
		

		//Reformate and add your test vectors from the prelab here following the example of the testvector above.	


		allPassed(passed, 12);
	end
      
endmodule

Lab8/NextPCLogicTest.vcd
$date
	Wed Nov  9 17:39:59 2022
$end
$version
	Icarus Verilog
$end
$timescale
	1ps
$end
$scope module NextPCLogicTest $end
$var wire 64 ! NextPC [63:0] $end
$var reg 1 " ALUZero $end
$var reg 1 # Branch $end
$var reg 64 $ CurrentPC [63:0] $end
$var reg 64 % SignExtImm64 [63:0] $end
$var reg 1 & Uncondbranch $end
$var reg 8 ' passed [7:0] $end
$scope module uut $end
$var wire 1 " ALUZero $end
$var wire 1 # Branch $end
$var wire 64 ( CurrentPC [63:0] $end
$var wire 64 ) SignExtImm64 [63:0] $end
$var wire 1 & Uncondbranch $end
$var reg 64 * NextPC [63:0] $end
$upscope $end
$scope task allPassed $end
$var reg 8 + numTests [7:0] $end
$var reg 8 , passed [7:0] $end
$upscope $end
$scope task passTest $end
$var reg 65 - actualOut [64:0] $end
$var reg 65 . expectedOut [64:0] $end
$var reg 8 / passed [7:0] $end
$var reg 121 0 testType [120:0] $end
$upscope $end
$upscope $end
$enddefinitions $end
#0
$dumpvars
bx 0
bx /
bx .
bx -
bx ,
bx +
b101 *
b10101011110011010000000000000000 )
b1 (
b0 '
0&
b10101011110011010000000000000000 %
b1 $
0#
0"
b101 !
$end
#40000
1"
b1 '
b1 /
b1011011100110010000100000001111010100011000100000011000010110111001100100001000000100001000100000001111010010000001000110 0
b101 .
b101 -
#80000
b1111111111111111111111111111111101010100001100110000000000000000 %
b1111111111111111111111111111111101010100001100110000000000000000 )
0"
b10 '
b10 /
#120000
1"
b11 '
b11 /
#160000
b10101011110011010000000000000000 %
b10101011110011010000000000000000 )
1#
0"
b100 '
b100 /
#200000
b1 %
b1 )
1"
b101 '
b101 /
#240000
b100 %
b100 )
0"
b110 '
b110 /
#280000
b1001 $
b1001 (
b1111111111111111111111111111111111111111111111111111111111111111 %
b1111111111111111111111111111111111111111111111111111111111111111 )
1"
b111 '
b111 /
b1011011100110010000100000001111010101010000100000011000010110111001100100001000000100001000100000001111010010000001000110 0
#320000
b1 $
b1 (
b1 %
b1 )
0#
0"
1&
b1000 '
b1000 /
#360000
b1001 '
b1001 /
b1011011100110010000100000001111010100011000100000011000010110111001100100001000000100001000100000001111010010000001000110 0
#400000
b1001 $
b1001 (
b1111111111111111111111111111111111111111111111111111111111111111 %
b1111111111111111111111111111111111111111111111111111111111111111 )
b1010 '
b1010 /
#440000
b1011 '
b1011 /
#480000
b1100 +
b1100 ,
b1100 '
b1100 /
