Lab7/SignExtender.v
module SignExtender(BusImm, Imm26, Ctrl); 
   output reg [63:0] BusImm; 
   input [25:0]  Imm26; 
   input [1:0] Ctrl; 
   
   //assign extBit = (Ctrl ? 2'b0 : Imm16[25]); //1'b0->2'b00 , 15->25
   //assign BusImm = {{26{extBit}}, Imm16}; //25->26 
   
   //-----------------
  always@(*) 
	begin
		case(Ctrl)
			2'b00: BusImm = {52'b0, Imm26[21:10]}; //ALUImm
			2'b01: BusImm = {{55{Imm26[20]}}, Imm26[20:12]}; //DTaddr
			2'b10: BusImm = {{36{Imm26[25]}}, Imm26, 2'b0}; //Baddr
			2'b11: BusImm = {{43{Imm26[23]}}, Imm26[23:5], 2'b0}; //CondBaddr
		endcase
	end
endmodule
   //assign ALUImm = {52'b0, ALU_immediate}
   //assign DTaddr = {55{DT_address[8]}, DT_address}
   //assign Baddr = {36{BR_address[25]}, BR_address, 2'b0}
   //assign CondBaddr = {43{COND_BR_address[25]}, COND_BR_address, 2'b0}

Lab7/SignExtender_tb.v
`timescale 1ns / 1ps

`define STRLEN 15
module SignExtender_tb;


   initial
     begin
      $dumpfile("SignExtender_tb.vcd");
      $dumpvars(0,SignExtender_tb);
     end
     
	task passTest;
		input [63:0] actualOut, expectedOut;
		input [`STRLEN*8:0] testType;
		inout [6:0] passed;
	
		if(actualOut == expectedOut) begin $display ("%s passed", testType); passed = passed + 1; end
		else $display ("%s failed: %h should be %h", testType, actualOut, expectedOut);
	endtask
	
	task allPassed;
		input [6:0] passed;
		input [6:0] numTests;
		
		if(passed == numTests) $display ("All tests passed");
		else $display("Some tests failed");
	endtask
	
	task stim;
		input [25:0] newIn;
		input [1:0] newSel;
		output [25:0] setIn;
		output [1:0]  setSel;
		
		begin
			#90;
			setIn = newIn;
			setSel = newSel;
		end
	endtask
	
	// Inputs
	reg [25:0] Imm26;
	reg [1:0] Ctrl;
	reg [6:0] passed;

	// Outputs
	wire [63:0] BusImm;

	// Instantiate the Unit Under Test (UUT)
	SignExtender uut (
		.Imm26(Imm26),
		.Ctrl(Ctrl), 
		.BusImm(BusImm)
	);

	initial begin
		// Initialize Inputs
		Imm26 = 0;
		Ctrl = 0;
		passed = 0;

		// Add stimulus here
		
		
		stim(26'b0, 2'b00, Imm26, Ctrl); #90; passTest(BusImm, 64'b0, "ALU immediate: ", passed);
		stim({{1'b1}, {25'b0}}, 2'b00, Imm26, Ctrl); #90; passTest(BusImm, 64'b0, "ALU immediate msb =1: ", passed);
		stim(21'b0, 2'b01, Imm26, Ctrl); #90; passTest(BusImm, 64'b0, "DT addr msb=0:", passed);
		stim({21{1'b1}}, 2'b01, Imm26, Ctrl); #90; passTest(BusImm, {64{1'b1}}, "DT addr msb=1:", passed);
		stim(26'b0, 2'b10, Imm26, Ctrl); #90; passTest(BusImm, 64'b0, "B addr msb=0:", passed);
		stim({{1'b1}, {25'b0}}, 2'b10, Imm26, Ctrl); #90; passTest(BusImm, {{37{1'b1}}, 27'b0}, "B addr msb=1:", passed);
		stim(26'b0, 2'b11, Imm26, Ctrl); #90 passTest(BusImm, 64'b0, "Cond B addr msb=0:", passed);
		stim({{1'b1},{23'b0}}, 2'b11, Imm26, Ctrl); #90 passTest(BusImm, {{44{1'b1}}, 20'b0}, "Cond B addr msb=1:", passed);		
		#90;
		
		//stim(26'b0, 2'b00, Imm26, Ctrl); #90; passTest(BusImm, 64'b0, "ALU immediate: ", passed);
		//stim(21'b0, 2'b01, Imm26, Ctrl); #90; passTest(BusImm, 64'b0, "DT addr msb=0:", passed);
		//stim({{1'b1}, {20'b0}}, 2'b01, Imm26, Ctrl); #90; passTest(BusImm, {{55'b1}, Imm26[20:12]}, "DT addr msb=1:", passed);
		//stim(26'b0, 2'b10, Imm26, Ctrl); #90; passTest(BusImm, 64'b0, "B addr msb=0:", passed);
		//stim({{1'b1}, {25'b0}}, 2'b10, Imm26, Ctrl); #90; passTest(BusImm, {{36'b1}, {25'b1}, {1'b0},{2'b1}}, "B addr msb=1:", passed);
		//stim(26'b0, 2'b11, Imm26, Ctrl); #90 passTest(BusImm, 64'b0, "Cond B addr msb=0:", passed);
		//stim({{1'b1},{25'b0}}, 2'b11, Imm26, Ctrl); #90 passTest(BusImm, {{43'b1}, Imm26[23:5], {2'b0}}, "Cond B addr msb=1:", passed);		
		//#90;
		
		
		allPassed(passed, 7);

	end
      
endmodule

Lab7/SignExtender_tb.vcd
$date
	Wed Nov  2 17:08:52 2022
$end
$version
	Icarus Verilog
$end
$timescale
	1ps
$end
$scope module SignExtender_tb $end
$var wire 64 ! BusImm [63:0] $end
$var reg 2 " Ctrl [1:0] $end
$var reg 26 # Imm26 [25:0] $end
$var reg 7 $ passed [6:0] $end
$scope module uut $end
$var wire 2 % Ctrl [1:0] $end
$var wire 26 & Imm26 [25:0] $end
$var reg 64 ' BusImm [63:0] $end
$upscope $end
$scope task allPassed $end
$var reg 7 ( numTests [6:0] $end
$var reg 7 ) passed [6:0] $end
$upscope $end
$scope task passTest $end
$var reg 64 * actualOut [63:0] $end
$var reg 64 + expectedOut [63:0] $end
$var reg 7 , passed [6:0] $end
$var reg 121 - testType [120:0] $end
$upscope $end
$scope task stim $end
$var reg 26 . newIn [25:0] $end
$var reg 2 / newSel [1:0] $end
$var reg 26 0 setIn [25:0] $end
$var reg 2 1 setSel [1:0] $end
$upscope $end
$upscope $end
$enddefinitions $end
#0
$dumpvars
bx 1
bx 0
b0 /
b0 .
bx -
bx ,
bx +
bx *
bx )
bx (
b0 '
b0 &
b0 %
b0 $
b0 #
b0 "
b0 !
$end
#90000
b0 1
b0 0
#180000
b10000000000000000000000000 .
b1 $
b1 ,
b10000010100110001010101001000000110100101101101011011010110010101100100011010010110000101110100011001010011101000100000 -
b0 +
b0 *
#270000
b10000000000000000000000000 #
b10000000000000000000000000 &
b10000000000000000000000000 0
#360000
b1 /
b0 .
b10 $
b10 ,
#450000
b1 "
b1 %
b0 #
b0 &
b1 1
b0 0
#540000
b111111111111111111111 .
b11 $
b11 ,
b100010001010100001000000110000101100100011001000111001000100000011011010111001101100010001111010011000000111010 -
#630000
b1111111111111111111111111111111111111111111111111111111111111111 !
b1111111111111111111111111111111111111111111111111111111111111111 '
b111111111111111111111 #
b111111111111111111111 &
b111111111111111111111 0
#720000
b10 /
b0 .
b100 $
b100 ,
b100010001010100001000000110000101100100011001000111001000100000011011010111001101100010001111010011000100111010 -
b1111111111111111111111111111111111111111111111111111111111111111 +
b1111111111111111111111111111111111111111111111111111111111111111 *
#810000
b0 !
b0 '
b10 "
b10 %
b0 #
b0 &
b10 1
b0 0
#900000
b10000000000000000000000000 .
b101 $
b101 ,
b1000010001000000110000101100100011001000111001000100000011011010111001101100010001111010011000000111010 -
b0 +
b0 *
#990000
b1111111111111111111111111111111111111000000000000000000000000000 !
b1111111111111111111111111111111111111000000000000000000000000000 '
b10000000000000000000000000 #
b10000000000000000000000000 &
b10000000000000000000000000 0
#1080000
b11 /
b0 .
b110 $
b110 ,
b1000010001000000110000101100100011001000111001000100000011011010111001101100010001111010011000100111010 -
b1111111111111111111111111111111111111000000000000000000000000000 +
b1111111111111111111111111111111111111000000000000000000000000000 *
#1170000
b0 !
b0 '
b11 "
b11 %
b0 #
b0 &
b11 1
b0 0
#1260000
b100000000000000000000000 .
b111 $
b111 ,
b11001000010000001000010001000000110000101100100011001000111001000100000011011010111001101100010001111010011000000111010 -
b0 +
b0 *
#1350000
b1111111111111111111111111111111111111111111100000000000000000000 !
b1111111111111111111111111111111111111111111100000000000000000000 '
b100000000000000000000000 #
b100000000000000000000000 &
b100000000000000000000000 0
#1440000
b1000 $
b1000 ,
b11001000010000001000010001000000110000101100100011001000111001000100000011011010111001101100010001111010011000100111010 -
b1111111111111111111111111111111111111111111100000000000000000000 +
b1111111111111111111111111111111111111111111100000000000000000000 *
#1530000
b111 (
b1000 )
